{"assets/.DS_Store":["assets/.DS_Store","assets/images/.DS_Store"],"assets/calculate_game.json":["assets/calculate_game.json"],"assets/classify_game_data.json":["assets/classify_game_data.json"],"assets/draw_game_data.json":["assets/draw_game_data.json"],"assets/draw_image_data.json":["assets/draw_image_data.json"],"assets/images/.DS_Store":["assets/images/.DS_Store"],"assets/images/alphabet.svg":["assets/images/alphabet.svg"],"assets/images/ball_type_1.svg":["assets/images/ball_type_1.svg"],"assets/images/ball_type_2.svg":["assets/images/ball_type_2.svg"],"assets/images/circle.svg":["assets/images/circle.svg"],"assets/images/completed_image_1.png":["assets/images/completed_image_1.png"],"assets/images/image_model_1.png":["assets/images/image_model_1.png"],"assets/images/puzzle_1.png":["assets/images/puzzle_1.png"],"assets/images/puzzle_1_0.png":["assets/images/puzzle_1_0.png"],"assets/images/puzzle_1_180.png":["assets/images/puzzle_1_180.png"],"assets/images/puzzle_1_270.png":["assets/images/puzzle_1_270.png"],"assets/images/puzzle_1_90.png":["assets/images/puzzle_1_90.png"],"assets/images/puzzle_1_result.png":["assets/images/puzzle_1_result.png"],"assets/images/puzzle_2.png":["assets/images/puzzle_2.png"],"assets/images/puzzle_2_0.png":["assets/images/puzzle_2_0.png"],"assets/images/puzzle_2_180.png":["assets/images/puzzle_2_180.png"],"assets/images/puzzle_2_270.png":["assets/images/puzzle_2_270.png"],"assets/images/puzzle_2_90.png":["assets/images/puzzle_2_90.png"],"assets/images/puzzle_2_result.png":["assets/images/puzzle_2_result.png"],"assets/images/puzzle_3.png":["assets/images/puzzle_3.png"],"assets/images/puzzle_3_0.png":["assets/images/puzzle_3_0.png"],"assets/images/puzzle_3_180.png":["assets/images/puzzle_3_180.png"],"assets/images/puzzle_3_270.png":["assets/images/puzzle_3_270.png"],"assets/images/puzzle_3_90.png":["assets/images/puzzle_3_90.png"],"assets/images/puzzle_3_result.png":["assets/images/puzzle_3_result.png"],"assets/images/puzzle_4.png":["assets/images/puzzle_4.png"],"assets/images/puzzle_4_0.png":["assets/images/puzzle_4_0.png"],"assets/images/puzzle_4_180.png":["assets/images/puzzle_4_180.png"],"assets/images/puzzle_4_270.png":["assets/images/puzzle_4_270.png"],"assets/images/puzzle_4_90.png":["assets/images/puzzle_4_90.png"],"assets/images/puzzle_4_result.png":["assets/images/puzzle_4_result.png"],"assets/images/puzzle_shadow_1.png":["assets/images/puzzle_shadow_1.png"],"assets/images/puzzle_shadow_2.png":["assets/images/puzzle_shadow_2.png"],"assets/images/puzzle_shadow_3.png":["assets/images/puzzle_shadow_3.png"],"assets/images/puzzle_shadow_4.png":["assets/images/puzzle_shadow_4.png"],"assets/images/rhino_body_1.svg":["assets/images/rhino_body_1.svg"],"assets/images/rhino_body_2.svg":["assets/images/rhino_body_2.svg"],"assets/images/rhino_body_3.svg":["assets/images/rhino_body_3.svg"],"assets/images/rhino_body_4.svg":["assets/images/rhino_body_4.svg"],"assets/images/rhino_head_1.svg":["assets/images/rhino_head_1.svg"],"assets/images/rhino_head_2.svg":["assets/images/rhino_head_2.svg"],"assets/images/rhino_head_3.svg":["assets/images/rhino_head_3.svg"],"assets/images/rhino_head_4.svg":["assets/images/rhino_head_4.svg"],"assets/images/ring.png":["assets/images/ring.png"],"assets/images/square.svg":["assets/images/square.svg"],"assets/images/triangle.svg":["assets/images/triangle.svg"],"assets/images/whale_1.svg":["assets/images/whale_1.svg"],"assets/images/whale_2.svg":["assets/images/whale_2.svg"],"assets/images/whale_3.svg":["assets/images/whale_3.svg"],"assets/images/whale_4.svg":["assets/images/whale_4.svg"],"assets/images/whale_5.svg":["assets/images/whale_5.svg"],"assets/images/whale_6.svg":["assets/images/whale_6.svg"],"assets/images/whale_7.svg":["assets/images/whale_7.svg"],"assets/images/whale_8.svg":["assets/images/whale_8.svg"],"assets/images/whale_model.svg":["assets/images/whale_model.svg"],"assets/images/whale_stroke.svg":["assets/images/whale_stroke.svg"],"assets/images_2.zip":["assets/images_2.zip"],"assets/jigsaw_game_data.json":["assets/jigsaw_game_data.json"],"assets/person.json":["assets/person.json"],"packages/cupertino_icons/assets/CupertinoIcons.ttf":["packages/cupertino_icons/assets/CupertinoIcons.ttf"]}